README.md
setup.cfg
setup.py
easy_tweet_deleter/__init__.py
easy_tweet_deleter/easy_tweet_deleter.py
easy_tweet_deleter.egg-info/PKG-INFO
easy_tweet_deleter.egg-info/SOURCES.txt
easy_tweet_deleter.egg-info/dependency_links.txt
easy_tweet_deleter.egg-info/requires.txt
easy_tweet_deleter.egg-info/top_level.txt