Metadata-Version: 2.1
Name: easy-tweet-deleter
Version: 0.0.2
Summary: A simple app to delete tweets
Home-page: https://github.com/TheTallBlonde1/easy_tweet_deleter
Author: Stefan Selby
Author-email: stefanselby@gmail.com
License: MIT
Download-URL: https://github.com/TheTallBlonde1/easy_tweet_deleter/archive/v_0_0_2.tar.gz
Keywords: DELETE,TWEETS,TWITTER
Platform: UNKNOWN
Classifier: Programming Language :: Python :: 3
Classifier: License :: Public Domain
Classifier: Operating System :: OS Independent
